lab 7/main_control.v
module main_control (
	input [3:0] funct,
	input [6:0] opcode,
	output [3:0] ALUop,
	output RegWrite
);

assign ALUop[0] = (~funct[3] & ~funct[2] & ~funct[1] & funct[0]) | (~funct[3] & funct[2] & funct[1] & ~funct[0]);
assign ALUop[1] = (~funct[2] & ~funct[1] & ~funct[0]) | (~funct[3] & funct[2] & ~funct[1] & funct[0]);
assign ALUop[2] = (funct[3] & ~funct[2] & ~funct[1] & ~funct[0]);
assign ALUop[3] = (~funct[3] & ~funct[1] & funct[0]);

assign RegWrite = 1;

endmodule

lab 8/PC.v
module PC (
	input [31:0] PC_in,
	output [31:0] PC_out,
	input clk,
	input rst
);

reg [31:0] PC;

always @(posedge clk or negedge rst) begin 
	if(!rst) begin 
		PC<=0;
	end
	else begin 
		PC <= PC_in;
	end
end

assign PC_out = PC;

endmodule

lab 8/pc_adder.v
`timescale 1ns / 1ps
//////////////////////////////////////////////////////////////////////////////////
// Company: 
// Engineer: 
// 
// Create Date: 03.02.2022 02:36:14
// Design Name: 
// Module Name: Adder_4_bit
// Project Name: 
// Target Devices: 
// Tool Versions: 
// Description: 
// 
// Dependencies: 
// 
// Revision:
// Revision 0.01 - File Created
// Additional Comments:
// 
//////////////////////////////////////////////////////////////////////////////////


module pc_adder(
    input [31:0] pc,
    output [31:0] next
    );
    
    assign next = pc+4;
    
endmodule

lab 7/reg_file.v
module reg_file (
	input clk,
	input rst,
	input writeReg,
	input [4:0] read_reg_num_1,
	input [4:0] read_reg_num_2,
	input [4:0] write_reg_num,
	input [31:0] write_data,
	output [31:0] read_data_1,
	output [31:0] read_data_2,
	output [31:0] regfile_out
);

reg [31:0] regfile [31:0];
integer i;

//reading block
assign read_data_1 = regfile[read_reg_num_1];
assign read_data_2 = regfile[read_reg_num_2];

//writing block
always @(posedge clk or negedge rst) begin 
	if(!rst) for(i = 0; i<32; i=i+1) regfile[i] <= 32'h1;
	else if (writeReg) begin 
		regfile[write_reg_num] = write_data;
	end
end

assign regfile_out = regfile[6];
endmodule

lab 8/instruction_memory.v
module instruction_memory (
	input [31:0] PC,
	input reset,
	output [31:0] instruction_code
);

reg [7:0]mem[36:0];

assign instruction_code = {mem[PC+3], mem[PC+2], mem[PC+1], mem[PC+0]};

always @(reset) begin 
	if(!reset) begin 
		{mem[3],mem[2],mem[1],mem[0]} = 32'h01c38333;
		{mem[7],mem[6],mem[5],mem[4]} = 32'h41c38333;
		{mem[11],mem[10],mem[9],mem[8]} = 32'h01c3f333;
		{mem[15],mem[14],mem[13],mem[12]} = 32'h01c3e333;
		{mem[19],mem[18],mem[17],mem[16]} = 32'h01c39333;
		{mem[23],mem[22],mem[21],mem[20]} = 32'h01c3d333;
	end
end

endmodule

assignment/ALU.v
`timescale 1ns / 1ps
//////////////////////////////////////////////////////////////////////////////////
// Company: 
// Engineer: 
// 
// Create Date: 10.02.2022 11:31:04
// Design Name: 
// Module Name: ALU
// Project Name: 
// Target Devices: 
// Tool Versions: 
// Description: 
// 
// Dependencies: 
// 
// Revision:
// Revision 0.01 - File Created
// Additional Comments:
// 
//////////////////////////////////////////////////////////////////////////////////


module ALU(
input wire [31:0] A, B,
input wire [3:0] cntrl,
output wire [31:0] Result,
output wire Zero
    );
    
    reg [31:0] res;
    always @(*) begin
        case(cntrl)
        4'b0000: res = A&B;
        4'b0001: res = A|B;
        4'b0010: res = A+B;
        4'b0110: res = A-B;
        4'b1001: res = A<<B;
        4'b1010: res = A>>B;
        4'b1000: res = (A < B) ? 32'd1: 32'd0;
        default: res = 32'bz;
        endcase 
        end
    assign Result = res;
    assign Zero = (Result == 0);    
endmodule

lab 7/processor_top.v
`include "main_control.v"
`include "PC.v"
`include "reg_file.v"
`include "instruction_memory.v"
`include "ALU.v"
`include "pc_adder.v"
module processor_top (
	input clk,
	input rst
);

wire [31:0] alu_in1, alu_in2, alu_res, instr, PC_in, PC_out;
wire RegWrite, Zero;
wire [3:0] ALUop;
wire [31:0] regfile;

ALU alu(alu_in1, alu_in2, ALUop, alu_res, Zero);
instruction_memory mem0(PC_out, rst, instr);
reg_file file0(clk, rst, RegWrite, instr[19:15], instr[24:20], instr[11:7], alu_res, alu_in1, alu_in2, regfile);
pc_adder pc_add0(PC_out, PC_in);
PC pc0(PC_in, PC_out, clk, rst);
main_control contr0({instr[30], instr[14:12]}, instr[6:0], ALUop, RegWrite);

endmodule

lab 8/processor_top_test.v
module processor_top_test ();

reg clk, rst;

	processor_top proc(clk, rst);

	initial begin 
		// $dumpfile("out.vcd");
		// $dumpvars;
		clk = 0;
		forever #5 clk = !clk;
	end

	initial begin 
		rst = 1;
		#1;
		rst = 0;
		#1;
		rst = 1;
		#200 $finish;
	end

endmodule

lab 7/yep.vcd
$date
	Thu Mar 24 08:38:53 2022
$end
$version
	Icarus Verilog
$end
$timescale
	1ps
$end
$scope module processor_top_test $end
$var reg 1 ! clk $end
$var reg 1 " rst $end
$scope module proc $end
$var wire 1 # RegWrite $end
$var wire 1 ! clk $end
$var wire 1 " rst $end
$var wire 32 $ regfile [31:0] $end
$var wire 32 % instr [31:0] $end
$var wire 32 & alu_res [31:0] $end
$var wire 32 ' alu_in2 [31:0] $end
$var wire 32 ( alu_in1 [31:0] $end
$var wire 1 ) Zero $end
$var wire 32 * PC_out [31:0] $end
$var wire 32 + PC_in [31:0] $end
$var wire 4 , ALUop [3:0] $end
$scope module alu $end
$var wire 4 - cntrl [3:0] $end
$var wire 1 ) Zero $end
$var wire 32 . Result [31:0] $end
$var wire 32 / B [31:0] $end
$var wire 32 0 A [31:0] $end
$var reg 32 1 res [31:0] $end
$upscope $end
$scope module contr0 $end
$var wire 1 # RegWrite $end
$var wire 4 2 funct [3:0] $end
$var wire 7 3 opcode [6:0] $end
$var wire 4 4 ALUop [3:0] $end
$upscope $end
$scope module file0 $end
$var wire 1 ! clk $end
$var wire 32 5 read_data_1 [31:0] $end
$var wire 32 6 read_data_2 [31:0] $end
$var wire 5 7 read_reg_num_1 [4:0] $end
$var wire 5 8 read_reg_num_2 [4:0] $end
$var wire 32 9 regfile_out [31:0] $end
$var wire 1 " rst $end
$var wire 1 # writeReg $end
$var wire 32 : write_data [31:0] $end
$var wire 5 ; write_reg_num [4:0] $end
$var integer 32 < i [31:0] $end
$upscope $end
$scope module mem0 $end
$var wire 1 " reset $end
$var wire 32 = instruction_code [31:0] $end
$var wire 32 > PC [31:0] $end
$upscope $end
$scope module pc0 $end
$var wire 32 ? PC_out [31:0] $end
$var wire 1 ! clk $end
$var wire 1 " rst $end
$var wire 32 @ PC_in [31:0] $end
$var reg 32 A PC [31:0] $end
$upscope $end
$scope module pc_add0 $end
$var wire 32 B pc [31:0] $end
$var wire 32 C next [31:0] $end
$upscope $end
$upscope $end
$upscope $end
$enddefinitions $end
#0
$dumpvars
bx C
bx B
bx A
bx @
bx ?
bx >
bx =
bx <
bx ;
bx :
bx 9
bx 8
bx 7
bx 6
bx 5
bx 4
bx 3
bx 2
bx 1
bx 0
bx /
bx .
bx -
bx ,
bx +
bx *
x)
bx (
bx '
bx &
bx %
bx $
1#
1"
0!
$end
#1000
0)
b10 ,
b10 -
b10 4
b10 &
b10 .
b10 1
b10 :
b110011 3
b110 ;
b1 (
b1 0
b1 5
b111 7
b0 2
b1 '
b1 /
b1 6
b11100 8
b1 $
b1 9
b100 +
b100 @
b100 C
b1110000111000001100110011 %
b1110000111000001100110011 =
b0 *
b0 >
b0 ?
b0 A
b0 B
b100000 <
0"
#2000
1"
#5000
1)
b0 &
b0 .
b0 1
b0 :
b110 ,
b110 -
b110 4
b1000 2
b1000 +
b1000 @
b1000 C
b1000001110000111000001100110011 %
b1000001110000111000001100110011 =
b100 *
b100 >
b100 ?
b100 A
b100 B
b10 $
b10 9
1!
#10000
0!
#15000
0)
b1 &
b1 .
b1 1
b1 :
b0 ,
b0 -
b0 4
b111 2
b1100 +
b1100 @
b1100 C
b1110000111111001100110011 %
b1110000111111001100110011 =
b1000 *
b1000 >
b1000 ?
b1000 A
b1000 B
b0 $
b0 9
1!
#20000
0!
#25000
b1 ,
b1 -
b1 4
b110 2
b10000 +
b10000 @
b10000 C
b1110000111110001100110011 %
b1110000111110001100110011 =
b1100 *
b1100 >
b1100 ?
b1100 A
b1100 B
b1 $
b1 9
1!
#30000
0!
#35000
0)
b10 &
b10 .
b10 1
b10 :
b1001 ,
b1001 -
b1001 4
b1 2
b10100 +
b10100 @
b10100 C
b1110000111001001100110011 %
b1110000111001001100110011 =
b10000 *
b10000 >
b10000 ?
b10000 A
b10000 B
1!
#40000
0!
#45000
1)
b0 &
b0 .
b0 1
b0 :
b1010 ,
b1010 -
b1010 4
b101 2
b11000 +
b11000 @
b11000 C
b1110000111101001100110011 %
b1110000111101001100110011 =
b10100 *
b10100 >
b10100 ?
b10100 A
b10100 B
b10 $
b10 9
1!
#50000
0!
#55000
bx ,
bx -
bx 4
x)
bz &
bz .
bz 1
bz :
bx 3
bx ;
bx (
bx 0
bx 5
bx 7
bx 2
bx '
bx /
bx 6
bx 8
b11100 +
b11100 @
b11100 C
bx %
bx =
b11000 *
b11000 >
b11000 ?
b11000 A
b11000 B
b0 $
b0 9
1!
#60000
0!
#65000
b100000 +
b100000 @
b100000 C
b11100 *
b11100 >
b11100 ?
b11100 A
b11100 B
1!
#70000
0!
#75000
b100100 +
b100100 @
b100100 C
b100000 *
b100000 >
b100000 ?
b100000 A
b100000 B
1!
#80000
0!
#85000
b101000 +
b101000 @
b101000 C
b100100 *
b100100 >
b100100 ?
b100100 A
b100100 B
1!
#90000
0!
#95000
b101100 +
b101100 @
b101100 C
b101000 *
b101000 >
b101000 ?
b101000 A
b101000 B
1!
#100000
0!
#105000
b110000 +
b110000 @
b110000 C
b101100 *
b101100 >
b101100 ?
b101100 A
b101100 B
1!
#110000
0!
#115000
b110100 +
b110100 @
b110100 C
b110000 *
b110000 >
b110000 ?
b110000 A
b110000 B
1!
#120000
0!
#125000
b111000 +
b111000 @
b111000 C
b110100 *
b110100 >
b110100 ?
b110100 A
b110100 B
1!
#130000
0!
#135000
b111100 +
b111100 @
b111100 C
b111000 *
b111000 >
b111000 ?
b111000 A
b111000 B
1!
#140000
0!
#145000
b1000000 +
b1000000 @
b1000000 C
b111100 *
b111100 >
b111100 ?
b111100 A
b111100 B
1!
#150000
0!
#155000
b1000100 +
b1000100 @
b1000100 C
b1000000 *
b1000000 >
b1000000 ?
b1000000 A
b1000000 B
1!
#160000
0!
#165000
b1001000 +
b1001000 @
b1001000 C
b1000100 *
b1000100 >
b1000100 ?
b1000100 A
b1000100 B
1!
#170000
0!
#175000
b1001100 +
b1001100 @
b1001100 C
b1001000 *
b1001000 >
b1001000 ?
b1001000 A
b1001000 B
1!
#180000
0!
#185000
b1010000 +
b1010000 @
b1010000 C
b1001100 *
b1001100 >
b1001100 ?
b1001100 A
b1001100 B
1!
#190000
0!
#195000
b1010100 +
b1010100 @
b1010100 C
b1010000 *
b1010000 >
b1010000 ?
b1010000 A
b1010000 B
1!
