assignment/assig/sign_extend.v
module sign_extend (
	input [20:0] in,
	output [31:0] out
);

assign out[31:21] = {11{in[20]}};
assign out [20:0] = in;

endmodule

assignment/assig/mux2to1.v
module mux2to1 (
	input [31:0] in1,
	input [31:0] in2,
	output [31:0] q,
	input sel
);

assign q = sel ? in2 : in1;

endmodule

assignment/main_control.v
module main_control (
	input [5:0] opcode,
	input [5:0] funct,
	output reg [3:0] ALUop,
	output reg regWrite,
	output reg Shift,
	output reg ImmSel
);

	always @(*) begin
		case (opcode)
			6'b111111: begin 
				ALUop = 4'h0;
				regWrite = 1;
				Shift = 0;
				ImmSel = 1;
			end

			6'b000000: begin 
				regWrite = 1;
				ImmSel = 0;
				ALUop[0] = (~funct[5] & ~funct[4] & ~funct[3] & ~funct[2] & ~funct[1] & ~funct[0]) | (funct[5] & ~funct[4] & ~funct[3] & funct[2] & ~funct[1] & funct[0]);
				ALUop[1] = (~funct[4] & ~funct[3] & ~funct[2] & funct[1] & ~funct[0]) | (funct[5] & ~funct[4] & ~funct[3] & ~funct[2] & ~funct[0]);
				ALUop[2] = (funct[5] & ~funct[4] & ~funct[3] & ~funct[2] & funct[1] & ~funct[0]);
				ALUop[3] = (~funct[5] & ~funct[4] & ~funct[3] & ~funct[2] & ~funct[0]);
				Shift = ALUop[3];
			end
			default : 	{ALUop, regWrite, Shift, ImmSel} = 0;
		endcase
	end

endmodule

lab 8/PC.v
module PC (
	input [31:0] PC_in,
	output [31:0] PC_out,
	input clk,
	input rst
);

reg [31:0] PC;

always @(posedge clk or negedge rst) begin 
	if(!rst) begin 
		PC<=0;
	end
	else begin 
		PC <= PC_in;
	end
end

assign PC_out = PC;

endmodule

lab 8/pc_adder.v
`timescale 1ns / 1ps
//////////////////////////////////////////////////////////////////////////////////
// Company: 
// Engineer: 
// 
// Create Date: 03.02.2022 02:36:14
// Design Name: 
// Module Name: Adder_4_bit
// Project Name: 
// Target Devices: 
// Tool Versions: 
// Description: 
// 
// Dependencies: 
// 
// Revision:
// Revision 0.01 - File Created
// Additional Comments:
// 
//////////////////////////////////////////////////////////////////////////////////


module pc_adder(
    input [31:0] pc,
    output [31:0] next
    );
    
    assign next = pc+4;
    
endmodule

assignment/assig/reg_file.v
module reg_file (
	input clk,
	input rst,
	input writeReg,
	input [4:0] read_reg_num_1,
	input [4:0] read_reg_num_2,
	input [4:0] write_reg_num,
	input [31:0] write_data,
	output [31:0] read_data_1,
	output [31:0] read_data_2,
	output [31:0] regfile_out_r0,
	output [31:0] regfile_out_r4,
	output [31:0] regfile_out_r8,
	output [31:0] regfile_out_r9,
	output [31:0] regfile_out_r11,
	output [31:0] regfile_out_r13,
	output [31:0] regfile_out_r10
);

reg [31:0] regfile [31:0];
integer i;

//reading block
assign read_data_1 = regfile[read_reg_num_1];
assign read_data_2 = regfile[read_reg_num_2];

//writing block
always @(posedge clk or negedge rst) begin 
	if(!rst) for(i = 0; i<32; i=i+1) regfile[i] <= 32'h1;
	else if (writeReg) begin 
		regfile[write_reg_num] = write_data;
	end
end

assign regfile_out_r0 = regfile[0];
assign regfile_out_r4 = regfile[4];
assign regfile_out_r8 = regfile[8];
assign regfile_out_r9 = regfile[9];
assign regfile_out_r11 = regfile[11];
assign regfile_out_r13 = regfile[13];
assign regfile_out_r10 = regfile[10];
endmodule

assignment/assig/instruction_memory.v
module instruction_memory (
	input [31:0] PC,
	input reset,
	output [31:0] instruction_code
);

reg [7:0]mem[36:0];

assign instruction_code = {mem[PC+3], mem[PC+2], mem[PC+1], mem[PC+0]};

always @(reset) begin 
	if(!reset) begin 
		{mem[3],mem[2],mem[1],mem[0]} = 32'h00011020;
		{mem[7],mem[6],mem[5],mem[4]} = 32'h00853022;
		{mem[11],mem[10],mem[9],mem[8]} = 32'h01095024;
		{mem[15],mem[14],mem[13],mem[12]} = 32'h01285025;
		{mem[19],mem[18],mem[17],mem[16]} = 32'h01660180;
		{mem[23],mem[22],mem[21],mem[20]} = 32'h01a90282;
		{mem[27],mem[26],mem[25],mem[24]} = 32'hFD455555;
	end
end

endmodule

assignment/ALU.v
`timescale 1ns / 1ps
//////////////////////////////////////////////////////////////////////////////////
// Company: 
// Engineer: 
// 
// Create Date: 10.02.2022 11:31:04
// Design Name: 
// Module Name: ALU
// Project Name: 
// Target Devices: 
// Tool Versions: 
// Description: 
// 
// Dependencies: 
// 
// Revision:
// Revision 0.01 - File Created
// Additional Comments:
// 
//////////////////////////////////////////////////////////////////////////////////


module ALU(
input wire [31:0] A, B,
input wire [3:0] cntrl,
output wire [31:0] Result,
output wire Zero
    );
    
    reg [31:0] res;
    always @(*) begin
        case(cntrl)
        4'b0000: res = A&B;
        4'b0001: res = A|B;
        4'b0010: res = A+B;
        4'b0110: res = A-B;
        4'b1001: res = A<<B;
        4'b1010: res = A>>B;
        4'b1000: res = (A < B) ? 32'd1: 32'd0;
        default: res = 32'bz;
        endcase 
        end
    assign Result = res;
    assign Zero = (Result == 0);    
endmodule

assignment/assig/processor_top.v
`include "main_control.v"
`include "PC.v"
`include "reg_file.v"
`include "instruction_memory.v"
`include "ALU.v"
`include "pc_adder.v"
`include "mux2to1.v"
`include "sign_extend.v"
module processor_top (
	input clk,
	input rst
);

wire [31:0] alu_in1, alu_in2, alu_res, instr, PC_in, PC_out, alumux_out, regfilemux_out, sign_extend_out;
wire RegWrite, Zero, ImmSel, Shift;
wire [3:0] ALUop;
wire [31:0] regfile_out_r0,regfile_out_r4,regfile_out_r8,regfile_out_r9,regfile_out_r11,regfile_out_r13,regfile_out_r10;

ALU alu(alu_in1, alumux_out, ALUop, alu_res, Zero);
instruction_memory mem0(PC_out, rst, instr);
reg_file file0(clk, rst, RegWrite, instr[20:16], instr[15:11], instr[25:21], regfilemux_out, alu_in1, alu_in2, regfile_out_r0,regfile_out_r4,regfile_out_r8,regfile_out_r9,regfile_out_r11,regfile_out_r13,regfile_out_r10);
pc_adder pc_add0(PC_out, PC_in);
PC pc0(PC_in, PC_out, clk, rst);
main_control contr0(instr[31:26], instr[5:0], ALUop, RegWrite, Shift, ImmSel);
mux2to1 ALUmux(alu_in2, instr[10:6], alumux_out, Shift);
mux2to1 regfilemux(alu_res, sign_extend_out, regfilemux_out, ImmSel);
sign_extend sign(instr[20:0], sign_extend_out);

endmodule

assignment/processor_top_test.v
module processor_top_test ();

reg clk, rst;

	processor_top proc(clk, rst);

	initial begin 
		$dumpfile("yep.vcd");
		$dumpvars;
		clk = 0;
		forever #5 clk = !clk;
	end

	initial begin 
		rst = 1;
		#1;
		rst = 0;
		#1;
		rst = 1;
		#200 $finish;
	end

endmodule

assignment/assig/yep.vcd
$date
	Sun Mar 27 15:11:00 2022
$end
$version
	Icarus Verilog
$end
$timescale
	1ps
$end
$scope module processor_top_test $end
$var reg 1 ! clk $end
$var reg 1 " rst $end
$scope module proc $end
$var wire 1 ! clk $end
$var wire 1 " rst $end
$var wire 32 # sign_extend_out [31:0] $end
$var wire 32 $ regfilemux_out [31:0] $end
$var wire 32 % regfile_out_r9 [31:0] $end
$var wire 32 & regfile_out_r8 [31:0] $end
$var wire 32 ' regfile_out_r4 [31:0] $end
$var wire 32 ( regfile_out_r13 [31:0] $end
$var wire 32 ) regfile_out_r11 [31:0] $end
$var wire 32 * regfile_out_r10 [31:0] $end
$var wire 32 + regfile_out_r0 [31:0] $end
$var wire 32 , instr [31:0] $end
$var wire 32 - alumux_out [31:0] $end
$var wire 32 . alu_res [31:0] $end
$var wire 32 / alu_in2 [31:0] $end
$var wire 32 0 alu_in1 [31:0] $end
$var wire 1 1 Zero $end
$var wire 1 2 Shift $end
$var wire 1 3 RegWrite $end
$var wire 32 4 PC_out [31:0] $end
$var wire 32 5 PC_in [31:0] $end
$var wire 1 6 ImmSel $end
$var wire 4 7 ALUop [3:0] $end
$scope module ALUmux $end
$var wire 32 8 in2 [31:0] $end
$var wire 1 2 sel $end
$var wire 32 9 q [31:0] $end
$var wire 32 : in1 [31:0] $end
$upscope $end
$scope module alu $end
$var wire 32 ; B [31:0] $end
$var wire 4 < cntrl [3:0] $end
$var wire 1 1 Zero $end
$var wire 32 = Result [31:0] $end
$var wire 32 > A [31:0] $end
$var reg 32 ? res [31:0] $end
$upscope $end
$scope module contr0 $end
$var wire 6 @ funct [5:0] $end
$var wire 6 A opcode [5:0] $end
$var reg 4 B ALUop [3:0] $end
$var reg 1 6 ImmSel $end
$var reg 1 2 Shift $end
$var reg 1 3 regWrite $end
$upscope $end
$scope module file0 $end
$var wire 1 ! clk $end
$var wire 32 C read_data_1 [31:0] $end
$var wire 32 D read_data_2 [31:0] $end
$var wire 5 E read_reg_num_1 [4:0] $end
$var wire 5 F read_reg_num_2 [4:0] $end
$var wire 32 G regfile_out_r0 [31:0] $end
$var wire 32 H regfile_out_r10 [31:0] $end
$var wire 32 I regfile_out_r11 [31:0] $end
$var wire 32 J regfile_out_r13 [31:0] $end
$var wire 32 K regfile_out_r4 [31:0] $end
$var wire 32 L regfile_out_r8 [31:0] $end
$var wire 32 M regfile_out_r9 [31:0] $end
$var wire 1 " rst $end
$var wire 1 3 writeReg $end
$var wire 5 N write_reg_num [4:0] $end
$var wire 32 O write_data [31:0] $end
$var integer 32 P i [31:0] $end
$upscope $end
$scope module mem0 $end
$var wire 1 " reset $end
$var wire 32 Q instruction_code [31:0] $end
$var wire 32 R PC [31:0] $end
$upscope $end
$scope module pc0 $end
$var wire 32 S PC_out [31:0] $end
$var wire 1 ! clk $end
$var wire 1 " rst $end
$var wire 32 T PC_in [31:0] $end
$var reg 32 U PC [31:0] $end
$upscope $end
$scope module pc_add0 $end
$var wire 32 V pc [31:0] $end
$var wire 32 W next [31:0] $end
$upscope $end
$scope module regfilemux $end
$var wire 32 X in1 [31:0] $end
$var wire 1 6 sel $end
$var wire 32 Y q [31:0] $end
$var wire 32 Z in2 [31:0] $end
$upscope $end
$scope module sign $end
$var wire 21 [ in [20:0] $end
$var wire 32 \ out [31:0] $end
$upscope $end
$upscope $end
$upscope $end
$enddefinitions $end
#0
$dumpvars
bx \
bx [
bx Z
bx Y
bx X
bx W
bx V
bx U
bx T
bx S
bx R
bx Q
bx P
bx O
bx N
bx M
bx L
bx K
bx J
bx I
bx H
bx G
bx F
bx E
bx D
bx C
bx B
bx A
bx @
bx ?
bx >
bx =
bx <
bx ;
bx :
bx 9
b0xxxxx 8
bx 7
x6
bx 5
bx 4
x3
x2
x1
bx 0
bx /
bx .
bx -
bx ,
bx +
bx *
bx )
bx (
bx '
bx &
bx %
bx $
bx #
1"
0!
$end
#1000
b10 $
b10 O
b10 Y
01
b10 .
b10 =
b10 ?
b10 X
b1 -
b1 9
b1 ;
02
b10 7
b10 <
b10 B
06
13
b100000 @
b0 8
b1 /
b1 :
b1 D
b10 F
b10001000000100000 #
b10001000000100000 Z
b10001000000100000 \
b10001000000100000 [
b1 0
b1 >
b1 C
b1 E
b0 A
b0 N
b1 (
b1 J
b1 )
b1 I
b1 *
b1 H
b1 %
b1 M
b1 &
b1 L
b1 '
b1 K
b1 +
b1 G
b100 5
b100 T
b100 W
b10001000000100000 ,
b10001000000100000 Q
b0 4
b0 R
b0 S
b0 U
b0 V
b100000 P
0"
#2000
1"
#5000
b0 $
b0 O
b0 Y
11
b0 .
b0 =
b0 ?
b0 X
b110 7
b110 <
b110 B
b100010 @
b110 F
b1010011000000100010 #
b1010011000000100010 Z
b1010011000000100010 \
b1010011000000100010 [
b100 N
b101 E
b1000 5
b1000 T
b1000 W
b100001010011000000100010 ,
b100001010011000000100010 Q
b100 4
b100 R
b100 S
b100 U
b100 V
b10 +
b10 G
1!
#10000
0!
#15000
b1 $
b1 O
b1 Y
01
b1 .
b1 =
b1 ?
b1 X
b0 7
b0 <
b0 B
b100100 @
b1010 F
b10010101000000100100 #
b10010101000000100100 Z
b10010101000000100100 \
b10010101000000100100 [
b1001 E
b1000 N
b1100 5
b1100 T
b1100 W
b1000010010101000000100100 ,
b1000010010101000000100100 Q
b1000 4
b1000 R
b1000 S
b1000 U
b1000 V
b0 '
b0 K
1!
#20000
0!
#25000
b1 7
b1 <
b1 B
b100101 @
b10000101000000100101 #
b10000101000000100101 Z
b10000101000000100101 \
b10000101000000100101 [
b1001 N
b1000 E
b10000 5
b10000 T
b10000 W
b1001010000101000000100101 ,
b1001010000101000000100101 Q
b1100 4
b1100 R
b1100 S
b1100 U
b1100 V
1!
#30000
0!
#35000
b1000000 $
b1000000 O
b1000000 Y
b1000000 .
b1000000 =
b1000000 ?
b1000000 X
12
b1001 7
b1001 <
b1001 B
b110 -
b110 9
b110 ;
b0 @
b110 8
b10 /
b10 :
b10 D
b0 F
b1100000000110000000 #
b1100000000110000000 Z
b1100000000110000000 \
b1100000000110000000 [
b1011 N
b110 E
b10100 5
b10100 T
b10100 W
b1011001100000000110000000 ,
b1011001100000000110000000 Q
b10000 4
b10000 R
b10000 S
b10000 U
b10000 V
1!
#40000
0!
#45000
b0 $
b0 O
b0 Y
11
b0 .
b0 =
b0 ?
b0 X
b1010 7
b1010 <
b1010 B
b1010 -
b1010 9
b1010 ;
b10 @
b1010 8
b10010000001010000010 #
b10010000001010000010 Z
b10010000001010000010 \
b10010000001010000010 [
b1101 N
b1001 E
b11000 5
b11000 T
b11000 W
b1101010010000001010000010 ,
b1101010010000001010000010 Q
b10100 4
b10100 R
b10100 S
b10100 U
b10100 V
b1000000 )
b1000000 I
1!
#50000
0!
#55000
b1010101010101010101 $
b1010101010101010101 O
b1010101010101010101 Y
01
b1 .
b1 =
b1 ?
b1 X
b1 -
b1 9
b1 ;
16
02
b0 7
b0 <
b0 B
b10101 @
b10101 8
b1 /
b1 :
b1 D
b1010 F
b1010101010101010101 #
b1010101010101010101 Z
b1010101010101010101 \
b1010101010101010101 [
b1010 N
b101 E
b111111 A
b11100 5
b11100 T
b11100 W
b11111101010001010101010101010101 ,
b11111101010001010101010101010101 Q
b11000 4
b11000 R
b11000 S
b11000 U
b11000 V
b0 (
b0 J
1!
#60000
0!
#65000
bx $
bx O
bx Y
x1
bx .
bx =
bx ?
bx X
03
06
bx @
b0xxxxx 8
bx F
bx #
bx Z
bx \
bx [
bx 0
bx >
bx C
bx E
bx A
bx N
b100000 5
b100000 T
b100000 W
bx ,
bx Q
b11100 4
b11100 R
b11100 S
b11100 U
b11100 V
bx -
bx 9
bx ;
bx /
bx :
bx D
b1010101010101010101 *
b1010101010101010101 H
1!
#70000
0!
#75000
b100100 5
b100100 T
b100100 W
b100000 4
b100000 R
b100000 S
b100000 U
b100000 V
1!
#80000
0!
#85000
b101000 5
b101000 T
b101000 W
b100100 4
b100100 R
b100100 S
b100100 U
b100100 V
1!
#90000
0!
#95000
b101100 5
b101100 T
b101100 W
b101000 4
b101000 R
b101000 S
b101000 U
b101000 V
1!
#100000
0!
#105000
b110000 5
b110000 T
b110000 W
b101100 4
b101100 R
b101100 S
b101100 U
b101100 V
1!
#110000
0!
#115000
b110100 5
b110100 T
b110100 W
b110000 4
b110000 R
b110000 S
b110000 U
b110000 V
1!
#120000
0!
#125000
b111000 5
b111000 T
b111000 W
b110100 4
b110100 R
b110100 S
b110100 U
b110100 V
1!
#130000
0!
#135000
b111100 5
b111100 T
b111100 W
b111000 4
b111000 R
b111000 S
b111000 U
b111000 V
1!
#140000
0!
#145000
b1000000 5
b1000000 T
b1000000 W
b111100 4
b111100 R
b111100 S
b111100 U
b111100 V
1!
#150000
0!
#155000
b1000100 5
b1000100 T
b1000100 W
b1000000 4
b1000000 R
b1000000 S
b1000000 U
b1000000 V
1!
#160000
0!
#165000
b1001000 5
b1001000 T
b1001000 W
b1000100 4
b1000100 R
b1000100 S
b1000100 U
b1000100 V
1!
#170000
0!
#175000
b1001100 5
b1001100 T
b1001100 W
b1001000 4
b1001000 R
b1001000 S
b1001000 U
b1001000 V
1!
#180000
0!
#185000
b1010000 5
b1010000 T
b1010000 W
b1001100 4
b1001100 R
b1001100 S
b1001100 U
b1001100 V
1!
#190000
0!
#195000
b1010100 5
b1010100 T
b1010100 W
b1010000 4
b1010000 R
b1010000 S
b1010000 U
b1010000 V
1!
